yake_rust-1.2.1.dist-info/METADATA
yake_rust-1.2.1.dist-info/WHEEL
yake_rust-1.2.1.dist-info/licenses/LICENSE
yake_rust.libs/libgcc_s-27e5a392.so.1
yake_rust/__init__.py
yake_rust/_lib.cpython-310-i386-linux-gnu.so
yake_rust/_lib.pyi
yake_rust/py.typed
yake_rust-1.2.1.dist-info/RECORD
