Metadata-Version: 2.4
Name: yake-rust
Version: 1.2.1
Classifier: Development Status :: 5 - Production/Stable
Classifier: Programming Language :: Python :: 3
Classifier: Programming Language :: Python :: 3.10
Classifier: Programming Language :: Python :: 3.11
Classifier: Programming Language :: Python :: 3.12
Classifier: Programming Language :: Python :: 3.13
Classifier: Programming Language :: Python :: 3.14
Classifier: Programming Language :: Rust
Classifier: Topic :: Scientific/Engineering :: Information Analysis
Classifier: Topic :: Software Development :: Libraries
Classifier: Topic :: Text Processing
Classifier: Topic :: Text Processing :: Linguistic
License-File: LICENSE
Summary: Python bindings for the yake-rust crate.
Author: Anton Vikström, Kyle Fahey, Igor Strebz
License-Expression: MIT
Requires-Python: >=3.10
Project-URL: Source Code, https://github.com/quesurifn/yake-rust
